super_collections/__init__.py
super_collections/shelf.py
super_collections-0.6.1.dist-info/licenses/LICENSE
super_collections-0.6.1.dist-info/METADATA
super_collections-0.6.1.dist-info/WHEEL
super_collections-0.6.1.dist-info/top_level.txt
super_collections-0.6.1.dist-info/RECORD
