Metadata-Version: 2.4
Name: super_collections
Version: 0.6.1
Summary: file: README.md
Author: Laurent Franceschetti
License: MIT
Project-URL: Source, https://github.com/fralau/super-collections
Classifier: License :: OSI Approved :: MIT License
Classifier: Programming Language :: Python :: 3
Classifier: Programming Language :: Python :: 3.8
Classifier: Programming Language :: Python :: 3.9
Classifier: Programming Language :: Python :: 3.10
Classifier: Programming Language :: Python :: 3.11
Classifier: Programming Language :: Python :: 3.12
Classifier: Programming Language :: Python :: 3.13
Requires-Python: >=3.8
License-File: LICENSE
Requires-Dist: hjson
Provides-Extra: test
Requires-Dist: pytest>=7.0; extra == "test"
Requires-Dist: rich; extra == "test"
Requires-Dist: pyyaml; extra == "test"
Dynamic: license-file
